Workbook

Sheet Assumptions
A1: Year | B1: 2024 | C1: 2025 | D1: 2026 | E1: 2027 | F1: 2028
A2: Revenue Growth % | C2: =C3+C4 -> 0.05 | D2: =D3+D4 -> 0.045 | E2: =E3+E4 -> 0.04 | F2: =F3+F4 -> 0.04
A3: Same Store Sales % | B3: 0.03 | C3: 0.035 | D3: 0.03 | E3: 0.025 | F3: 0.025
A4: New Store Growth % | B4: 0.02 | C4: 0.015 | D4: 0.015 | E4: 0.015 | F4: 0.015
A5: EBITDA Margin % | B5: 0.35 | C5: 0.355 | D5: 0.36 | E5: 0.365 | F5: 0.37
A6: Depreciation % of Revenue | B6: 0.05 | C6: 0.05 | D6: 0.05 | E6: 0.05 | F6: 0.05
A7: Tax Rate % | B7: 0.21 | C7: 0.21 | D7: 0.21 | E7: 0.21 | F7: 0.21
A8: Interest Rate % | B8: 0.05 | C8: 0.05 | D8: 0.05 | E8: 0.05 | F8: 0.05
A9: CapEx per Store | B9: 5000 | C9: 5200 | D9: 5400 | E9: 5600 | F9: 5800
A10: Store Count | B10: 19500 | C10: =B10*(1+C4) -> 19792.5 | D10: =C10*(1+D4) -> 20089.388 | E10: =D10*(1+E4) -> 20390.728 | F10: =E10*(1+F4) -> 20696.589
A12: Notes:
A13: All figures USD millions except CapEx per Store ($) & Store Count (units).
A14: 2024 = base/actual year (hard-coded). 2025-2028 = live formulas.
A15: COGS = 40% of revenue; SG&A is the plug so EBITDA = EBITDA Margin %.

Sheet IS
A1: Line Item | B1: 2024 | C1: 2025 | D1: 2026 | E1: 2027 | F1: 2028
A2: Revenue | B2: 2000 | C2: =B2*(1+Assumptions!C2) -> 2100 | D2: =C2*(1+Assumptions!D2) -> 2194.5 | E2: =D2*(1+Assumptions!E2) -> 2282.28 | F2: =E2*(1+Assumptions!F2) -> 2373.5712
A3: COGS | B3: =B2*0.4 -> 800 | C3: =C2*0.4 -> 840 | D3: =D2*0.4 -> 877.8 | E3: =E2*0.4 -> 912.912 | F3: =F2*0.4 -> 949.42848
A4: Gross Profit | B4: =B2-B3 -> 1200 | C4: =C2-C3 -> 1260 | D4: =D2-D3 -> 1316.7 | E4: =E2-E3 -> 1369.368 | F4: =F2-F3 -> 1424.1427
A5: Gross Margin % | B5: =B4/B2 -> 0.6 | C5: =C4/C2 -> 0.6 | D5: =D4/D2 -> 0.6 | E5: =E4/E2 -> 0.6 | F5: =F4/F2 -> 0.6
A6: SG&A | B6: =B4-B7 -> 500 | C6: =C4-C7 -> 514.5 | D6: =D4-D7 -> 526.68 | E6: =E4-E7 -> 536.3358 | F6: =F4-F7 -> 545.92138
A7: EBITDA | B7: =B2*Assumptions!B5 -> 700 | C7: =C2*Assumptions!C5 -> 745.5 | D7: =D2*Assumptions!D5 -> 790.02 | E7: =E2*Assumptions!E5 -> 833.0322 | F7: =F2*Assumptions!F5 -> 878.22134
A8: Depreciation | B8: =B2*Assumptions!B6 -> 100 | C8: =C2*Assumptions!C6 -> 105 | D8: =D2*Assumptions!D6 -> 109.725 | E8: =E2*Assumptions!E6 -> 114.114 | F8: =F2*Assumptions!F6 -> 118.67856
A9: EBIT | B9: =B7-B8 -> 600 | C9: =C7-C8 -> 640.5 | D9: =D7-D8 -> 680.295 | E9: =E7-E8 -> 718.9182 | F9: =F7-F8 -> 759.54278
A10: Interest Expense | B10: =Assumptions!B8*(BS!B17+BS!B20) -> 175 | C10: =Assumptions!C8*(BS!C17+BS!C20) -> 170 | D10: =Assumptions!D8*(BS!D17+BS!D20) -> 165 | E10: =Assumptions!E8*(BS!E17+BS!E20) -> 160 | F10: =Assumptions!F8*(BS!F17+BS!F20) -> 155
A11: Pre-Tax Income | B11: =B9-B10 -> 425 | C11: =C9-C10 -> 470.5 | D11: =D9-D10 -> 515.295 | E11: =E9-E10 -> 558.9182 | F11: =F9-F10 -> 604.54278
A12: Taxes | B12: =B11*Assumptions!B7 -> 89.25 | C12: =C11*Assumptions!C7 -> 98.805 | D12: =D11*Assumptions!D7 -> 108.21195 | E12: =E11*Assumptions!E7 -> 117.37282 | F12: =F11*Assumptions!F7 -> 126.95399
A13: Net Income | B13: =B11-B12 -> 335.75 | C13: =C11-C12 -> 371.695 | D13: =D11-D12 -> 407.08305 | E13: =E11-E12 -> 441.54538 | F13: =F11-F12 -> 477.5888

Sheet BS
A1: Line Item | B1: 2024 | C1: 2025 | D1: 2026 | E1: 2027 | F1: 2028
A2: ASSETS
A3: Cash | B3: =CF!B13 -> 850 | C3: =CF!C13 -> 941.9265 | D3: =CF!D13 -> 1050.4903 | E3: =CF!E13 -> 1174.7001 | F3: =CF!F13 -> 1315.7845
A4: Accounts Receivable | B4: 80 | C4: =B4*IS!C2/IS!B2 -> 84 | D4: =C4*IS!D2/IS!C2 -> 87.78 | E4: =D4*IS!E2/IS!D2 -> 91.2912 | F4: =E4*IS!F2/IS!E2 -> 94.942848
A5: Inventory | B5: 20 | C5: =B5*IS!C2/IS!B2 -> 21 | D5: =C5*IS!D2/IS!C2 -> 21.945 | E5: =D5*IS!E2/IS!D2 -> 22.8228 | F5: =E5*IS!F2/IS!E2 -> 23.735712
A6: Prepaid Expenses | B6: 40 | C6: =B6*IS!C2/IS!B2 -> 42 | D6: =C6*IS!D2/IS!C2 -> 43.89 | E6: =D6*IS!E2/IS!D2 -> 45.6456 | F6: =E6*IS!F2/IS!E2 -> 47.471424
A7: Total Current Assets | B7: =SUM(B3:B6) -> 990 | C7: =SUM(C3:C6) -> 1088.9265 | D7: =SUM(D3:D6) -> 1204.1053 | E7: =SUM(E3:E6) -> 1334.4597 | F7: =SUM(F3:F6) -> 1481.9345
A8: PP&E | B8: 1200 | C8: =B8+Assumptions!C9*Assumptions!C10/1000000-IS!C8 -> 1197.921 | D8: =C8+Assumptions!D9*Assumptions!D10/1000000-IS!D8 -> 1196.6787 | E8: =D8+Assumptions!E9*Assumptions!E10/1000000-IS!E8 -> 1196.7528 | F8: =E8+Assumptions!F9*Assumptions!F10/1000000-IS!F8 -> 1198.1144
A9: Right-of-Use Assets | B9: 1200 | C9: =B9 -> 1200 | D9: =C9 -> 1200 | E9: =D9 -> 1200 | F9: =E9 -> 1200
A10: Intangibles | B10: 1000 | C10: =B10 -> 1000 | D10: =C10 -> 1000 | E10: =D10 -> 1000 | F10: =E10 -> 1000
A11: Goodwill | B11: 5500 | C11: =B11 -> 5500 | D11: =C11 -> 5500 | E11: =D11 -> 5500 | F11: =E11 -> 5500
A12: Total Non-Current Assets | B12: =SUM(B8:B11) -> 8900 | C12: =SUM(C8:C11) -> 8897.921 | D12: =SUM(D8:D11) -> 8896.6787 | E12: =SUM(E8:E11) -> 8896.7528 | F12: =SUM(F8:F11) -> 8898.1144
A13: TOTAL ASSETS | B13: =B7+B12 -> 9890 | C13: =C7+C12 -> 9986.8475 | D13: =D7+D12 -> 10100.784 | E13: =E7+E12 -> 10231.213 | F13: =F7+F12 -> 10380.049
A14: LIABILITIES
A15: Accounts Payable | B15: 100 | C15: =B15*IS!C2/IS!B2 -> 105 | D15: =C15*IS!D2/IS!C2 -> 109.725 | E15: =D15*IS!E2/IS!D2 -> 114.114 | F15: =E15*IS!F2/IS!E2 -> 118.67856
A16: Accrued Expenses | B16: 120 | C16: =B16*IS!C2/IS!B2 -> 126 | D16: =C16*IS!D2/IS!C2 -> 131.67 | E16: =D16*IS!E2/IS!D2 -> 136.9368 | F16: =E16*IS!F2/IS!E2 -> 142.41427
A17: Short-term Debt | B17: 200 | C17: =B17 -> 200 | D17: =C17 -> 200 | E17: =D17 -> 200 | F17: =E17 -> 200
A18: Current Lease Liability | B18: 150 | C18: =B18 -> 150 | D18: =C18 -> 150 | E18: =D18 -> 150 | F18: =E18 -> 150
A19: Total Current Liabilities | B19: =SUM(B15:B18) -> 570 | C19: =SUM(C15:C18) -> 581 | D19: =SUM(D15:D18) -> 591.395 | E19: =SUM(E15:E18) -> 601.0508 | F19: =SUM(F15:F18) -> 611.09283
A20: Long-term Debt | B20: 3300 | C20: =B20-100 -> 3200 | D20: =C20-100 -> 3100 | E20: =D20-100 -> 3000 | F20: =E20-100 -> 2900
A21: Lease Liabilities | B21: 1150 | C21: =B21 -> 1150 | D21: =C21 -> 1150 | E21: =D21 -> 1150 | F21: =E21 -> 1150
A22: Deferred Tax | B22: 300 | C22: =B22 -> 300 | D22: =C22 -> 300 | E22: =D22 -> 300 | F22: =E22 -> 300
A23: Total Non-Current Liabilities | B23: =SUM(B20:B22) -> 4750 | C23: =SUM(C20:C22) -> 4650 | D23: =SUM(D20:D22) -> 4550 | E23: =SUM(E20:E22) -> 4450 | F23: =SUM(F20:F22) -> 4350
A24: TOTAL LIABILITIES | B24: =B19+B23 -> 5320 | C24: =C19+C23 -> 5231 | D24: =D19+D23 -> 5141.395 | E24: =E19+E23 -> 5051.0508 | F24: =F19+F23 -> 4961.0928
A25: EQUITY
A26: Share Capital | B26: 100 | C26: =B26 -> 100 | D26: =C26 -> 100 | E26: =D26 -> 100 | F26: =E26 -> 100
A27: Retained Earnings | B27: 2970 | C27: =B27+IS!C13+CF!C9 -> 3155.8475 | D27: =C27+IS!D13+CF!D9 -> 3359.389 | E27: =D27+IS!E13+CF!E9 -> 3580.1617 | F27: =E27+IS!F13+CF!F9 -> 3818.9561
A28: Additional Paid-In Capital | B28: 2000 | C28: =B28 -> 2000 | D28: =C28 -> 2000 | E28: =D28 -> 2000 | F28: =E28 -> 2000
A29: Treasury Stock | B29: -500 | C29: =B29 -> -500 | D29: =C29 -> -500 | E29: =D29 -> -500 | F29: =E29 -> -500
A30: TOTAL EQUITY | B30: =B26+B27+B28+B29 -> 4570 | C30: =C26+C27+C28+C29 -> 4755.8475 | D30: =D26+D27+D28+D29 -> 4959.389 | E30: =E26+E27+E28+E29 -> 5180.1617 | F30: =F26+F27+F28+F29 -> 5418.9561
A31: TOTAL LIABILITIES + EQUITY | B31: =B24+B30 -> 9890 | C31: =C24+C30 -> 9986.8475 | D31: =D24+D30 -> 10100.784 | E31: =E24+E30 -> 10231.213 | F31: =F24+F30 -> 10380.049
A32: Balance Check (must = 0) | B32: =B13-B31 -> 0 | C32: =C13-C31 -> 0 | D32: =D13-D31 -> 0 | E32: =E13-E31 -> 0 | F32: =F13-F31 -> 0

Sheet CF
A1: Line Item | B1: 2024 | C1: 2025 | D1: 2026 | E1: 2027 | F1: 2028
A2: Net Income | B2: =IS!B13 -> 335.75 | C2: =IS!C13 -> 371.695 | D2: =IS!D13 -> 407.08305 | E2: =IS!E13 -> 441.54538 | F2: =IS!F13 -> 477.5888
A3: Depreciation | B3: =IS!B8 -> 100 | C3: =IS!C8 -> 105 | D3: =IS!D8 -> 109.725 | E3: =IS!E8 -> 114.114 | F3: =IS!F8 -> 118.67856
A4: Change in Working Capital | B4: 3.81 | C4: =-((BS!C4-BS!B4)+(BS!C5-BS!B5)+(BS!C6-BS!B6))+((BS!C15-BS!B15)+(BS!C16-BS!B16)) -> 4 | D4: =-((BS!D4-BS!C4)+(BS!D5-BS!C5)+(BS!D6-BS!C6))+((BS!D15-BS!C15)+(BS!D16-BS!C16)) -> 3.78 | E4: =-((BS!E4-BS!D4)+(BS!E5-BS!D5)+(BS!E6-BS!D6))+((BS!E15-BS!D15)+(BS!E16-BS!D16)) -> 3.5112 | F4: =-((BS!F4-BS!E4)+(BS!F5-BS!E5)+(BS!F6-BS!E6))+((BS!F15-BS!E15)+(BS!F16-BS!E16)) -> 3.651648
A5: Operating Cash Flow | B5: =B2+B3+B4 -> 439.56 | C5: =C2+C3+C4 -> 480.695 | D5: =D2+D3+D4 -> 520.58805 | E5: =E2+E3+E4 -> 559.17058 | F5: =F2+F3+F4 -> 599.91901
A6: CapEx | B6: =-Assumptions!B9*Assumptions!B10/1000000 -> -97.5 | C6: =-Assumptions!C9*Assumptions!C10/1000000 -> -102.921 | D6: =-Assumptions!D9*Assumptions!D10/1000000 -> -108.48269 | E6: =-Assumptions!E9*Assumptions!E10/1000000 -> -114.18808 | F6: =-Assumptions!F9*Assumptions!F10/1000000 -> -120.04022
A7: Investing Cash Flow | B7: =B6 -> -97.5 | C7: =C6 -> -102.921 | D7: =D6 -> -108.48269 | E7: =E6 -> -114.18808 | F7: =F6 -> -120.04022
A8: Debt Issued/(Repaid) | B8: -100 | C8: =BS!C20-BS!B20 -> -100 | D8: =BS!D20-BS!C20 -> -100 | E8: =BS!E20-BS!D20 -> -100 | F8: =BS!F20-BS!E20 -> -100
A9: Dividends | B9: =-0.5*IS!B13 -> -167.875 | C9: =-0.5*IS!C13 -> -185.8475 | D9: =-0.5*IS!D13 -> -203.54153 | E9: =-0.5*IS!E13 -> -220.77269 | F9: =-0.5*IS!F13 -> -238.7944
A10: Financing Cash Flow | B10: =B8+B9 -> -267.875 | C10: =C8+C9 -> -285.8475 | D10: =D8+D9 -> -303.54152 | E10: =E8+E9 -> -320.77269 | F10: =F8+F9 -> -338.7944
A11: Net Change in Cash | B11: =B5+B7+B10 -> 74.185 | C11: =C5+C7+C10 -> 91.9265 | D11: =D5+D7+D10 -> 108.56383 | E11: =E5+E7+E10 -> 124.20981 | F11: =F5+F7+F10 -> 141.08439
A12: Opening Cash | B12: 775.815 | C12: =B13 -> 850 | D12: =C13 -> 941.9265 | E12: =D13 -> 1050.4903 | F12: =E13 -> 1174.7001
A13: Closing Cash | B13: =B12+B11 -> 850 | C13: =C12+C11 -> 941.9265 | D13: =D12+D11 -> 1050.4903 | E13: =E12+E11 -> 1174.7001 | F13: =F12+F11 -> 1315.7845
A14: Interest Paid (memo; already in Net Income) | B14: =-IS!B10 -> -175 | C14: =-IS!C10 -> -170 | D14: =-IS!D10 -> -165 | E14: =-IS!E10 -> -160 | F14: =-IS!F10 -> -155

Sheet Ratios
A1: Year | B1: 2024 | C1: 2025 | D1: 2026 | E1: 2027 | F1: 2028
A2: Revenue Growth % | C2: =IS!C2/IS!B2-1 -> 0.05 | D2: =IS!D2/IS!C2-1 -> 0.045 | E2: =IS!E2/IS!D2-1 -> 0.04 | F2: =IS!F2/IS!E2-1 -> 0.04
A3: EBITDA Margin % | B3: =IS!B7/IS!B2 -> 0.35 | C3: =IS!C7/IS!C2 -> 0.355 | D3: =IS!D7/IS!D2 -> 0.36 | E3: =IS!E7/IS!E2 -> 0.365 | F3: =IS!F7/IS!F2 -> 0.37
A4: Net Margin % | B4: =IS!B13/IS!B2 -> 0.167875 | C4: =IS!C13/IS!C2 -> 0.176998 | D4: =IS!D13/IS!D2 -> 0.185502 | E4: =IS!E13/IS!E2 -> 0.193467 | F4: =IS!F13/IS!F2 -> 0.201211
A5: Debt / EBITDA | B5: =(BS!B17+BS!B20)/IS!B7 -> 5 | C5: =(BS!C17+BS!C20)/IS!C7 -> 4.560698 | D5: =(BS!D17+BS!D20)/IS!D7 -> 4.177109 | E5: =(BS!E17+BS!E20)/IS!E7 -> 3.841388 | F5: =(BS!F17+BS!F20)/IS!F7 -> 3.529862
A6: Interest Coverage (EBIT / Interest) | B6: =IS!B9/IS!B10 -> 3.428571 | C6: =IS!C9/IS!C10 -> 3.767647 | D6: =IS!D9/IS!D10 -> 4.123 | E6: =IS!E9/IS!E10 -> 4.493239 | F6: =IS!F9/IS!F10 -> 4.900276
A7: ROE % | B7: =IS!B13/BS!B30 -> 0.073468 | C7: =IS!C13/BS!C30 -> 0.078155 | D7: =IS!D13/BS!D30 -> 0.082083 | E7: =IS!E13/BS!E30 -> 0.085238 | F7: =IS!F13/BS!F30 -> 0.088133
A8: Free Cash Flow | B8: =CF!B5+CF!B6 -> 342.06 | C8: =CF!C5+CF!C6 -> 377.774 | D8: =CF!D5+CF!D6 -> 412.10536 | E8: =CF!E5+CF!E6 -> 444.9825 | F8: =CF!F5+CF!F6 -> 479.87879
